canvas_mcp/__init__.py
canvas_mcp/server.py
canvas_mcp/code_api/README.md
canvas_mcp/code_api/client.ts
canvas_mcp/code_api/index.ts
canvas_mcp/code_api/canvas/index.ts
canvas_mcp/code_api/canvas/assignments/index.ts
canvas_mcp/code_api/canvas/assignments/listSubmissions.ts
canvas_mcp/code_api/canvas/communications/index.ts
canvas_mcp/code_api/canvas/communications/sendMessage.ts
canvas_mcp/code_api/canvas/courses/getCourseDetails.ts
canvas_mcp/code_api/canvas/courses/index.ts
canvas_mcp/code_api/canvas/courses/listCourses.ts
canvas_mcp/code_api/canvas/discussions/bulkGradeDiscussion.ts
canvas_mcp/code_api/canvas/discussions/index.ts
canvas_mcp/code_api/canvas/discussions/listDiscussions.ts
canvas_mcp/code_api/canvas/discussions/postEntry.ts
canvas_mcp/code_api/canvas/grading/bulkGrade.ts
canvas_mcp/code_api/canvas/grading/gradeWithRubric.ts
canvas_mcp/code_api/canvas/grading/index.ts
canvas_mcp/core/__init__.py
canvas_mcp/core/anonymization.py
canvas_mcp/core/cache.py
canvas_mcp/core/client.py
canvas_mcp/core/config.py
canvas_mcp/core/dates.py
canvas_mcp/core/file_validation.py
canvas_mcp/core/logging.py
canvas_mcp/core/peer_review_comments.py
canvas_mcp/core/peer_reviews.py
canvas_mcp/core/types.py
canvas_mcp/core/validation.py
canvas_mcp/resources/__init__.py
canvas_mcp/resources/resources.py
canvas_mcp/tools/__init__.py
canvas_mcp/tools/accessibility.py
canvas_mcp/tools/assignments.py
canvas_mcp/tools/code_execution.py
canvas_mcp/tools/courses.py
canvas_mcp/tools/discovery.py
canvas_mcp/tools/discussions.py
canvas_mcp/tools/files.py
canvas_mcp/tools/message_templates.py
canvas_mcp/tools/messaging.py
canvas_mcp/tools/modules.py
canvas_mcp/tools/other_tools.py
canvas_mcp/tools/pages.py
canvas_mcp/tools/peer_review_comments.py
canvas_mcp/tools/peer_reviews.py
canvas_mcp/tools/rubrics.py
canvas_mcp/tools/student_tools.py
canvas_mcp-1.0.7.dist-info/METADATA
canvas_mcp-1.0.7.dist-info/WHEEL
canvas_mcp-1.0.7.dist-info/entry_points.txt
canvas_mcp-1.0.7.dist-info/licenses/LICENSE
canvas_mcp-1.0.7.dist-info/RECORD
