Metadata-Version: 2.4
Name: canvas-mcp
Version: 1.0.7
Summary: A Model Context Protocol server for Canvas LMS integration
Project-URL: Homepage, https://github.com/vishalsachdev/canvas-mcp
Project-URL: Repository, https://github.com/vishalsachdev/canvas-mcp
Project-URL: Documentation, https://github.com/vishalsachdev/canvas-mcp/blob/main/README.md
Project-URL: Issues, https://github.com/vishalsachdev/canvas-mcp/issues
Author-email: Vishal Sachdev <vishal@example.com>
License: MIT License
License-File: LICENSE
Keywords: api,canvas,claude,education,lms,mcp
Classifier: Development Status :: 4 - Beta
Classifier: Intended Audience :: Education
Classifier: License :: OSI Approved :: MIT License
Classifier: Operating System :: OS Independent
Classifier: Programming Language :: Python :: 3
Classifier: Programming Language :: Python :: 3.10
Classifier: Programming Language :: Python :: 3.11
Classifier: Programming Language :: Python :: 3.12
Classifier: Topic :: Education
Classifier: Topic :: Internet :: WWW/HTTP :: Dynamic Content :: Content Management System
Requires-Python: >=3.10
Requires-Dist: fastmcp>=2.14.0
Requires-Dist: httpx>=0.28.1
Requires-Dist: pydantic>=2.12.0
Requires-Dist: python-dateutil>=2.8.0
Requires-Dist: python-dotenv>=1.0.0
Requires-Dist: requests>=2.32.0
Provides-Extra: dev
Requires-Dist: black>=23.0.0; extra == 'dev'
Requires-Dist: mypy>=1.5.0; extra == 'dev'
Requires-Dist: pytest-asyncio>=0.21.0; extra == 'dev'
Requires-Dist: pytest>=7.0.0; extra == 'dev'
Requires-Dist: ruff>=0.1.0; extra == 'dev'
